AUTHORS.rst
CHANGES.rst
LICENSE
MANIFEST.in
README.rst
setup.py
./transmeta/__init__.py
./transmeta/management/__init__.py
./transmeta/management/commands/__init__.py
./transmeta/management/commands/sync_transmeta_db.py
django_transmeta_jl.egg-info/PKG-INFO
django_transmeta_jl.egg-info/SOURCES.txt
django_transmeta_jl.egg-info/dependency_links.txt
django_transmeta_jl.egg-info/not-zip-safe
django_transmeta_jl.egg-info/top_level.txt